{
	"type": "object",
	"properties": {
		"@context": {
			"type": "string",
			"const": "https://schema.twindev.org/immutable-storage/",
			"description": "JSON-LD Context."
		},
		"type": {
			"type": "string",
			"const": "ImmutableStorageEntityStorageReceipt",
			"description": "JSON-LD Type."
		},
		"entityStorageId": {
			"type": "string",
			"description": "The entity storage Id."
		}
	},
	"required": [
		"@context",
		"type",
		"entityStorageId"
	],
	"additionalProperties": false,
	"description": "Receipt for the entity storage Immutable Storage connector."
}